[{"Id":"33004144","DhId":"de:14627:4144","Place":"","Name":"Weinböhla (Rathausstraße)","Longitude":4609670,"Latitude":5670577,"Position":"Previous","Platform":{"Name":"1","Type":"Platform"},"Time":"2022-02-21 03:46:00","RealTime":"2022-02-21 03:46:00","State":"InTime"},{"Id":"33004139","DhId":"de:14627:4139","Place":"","Name":"Weinböhla Gellertstraße","Longitude":4609868,"Latitude":5670306,"Position":"Previous","Platform":{"Name":"1","Type":"Platform"},"Time":"2022-02-21 03:47:00","RealTime":"2022-02-21 03:47:00","State":"InTime"},{"Id":"33004147","DhId":"de:14627:4147","Place":"","Name":"Weinböhla Köhlerstraße","Longitude":4610221,"Latitude":5669732,"Position":"Previous","Platform":{"Name":"3","Type":"Platform"},"Time":"2022-02-21 03:48:00","RealTime":"2022-02-21 03:48:00","State":"InTime"},{"Id":"33004158","DhId":"de:14627:4158","Place":"","Name":"Coswig Steinbacher Weg","Longitude":4610123,"Latitude":5668843,"Position":"Previous","Platform":{"Name":"1","Type":"Platform"},"Time":"2022-02-21 03:50:00","RealTime":"2022-02-21 03:50:00","State":"InTime"},{"Id":"33004157","DhId":"de:14627:4157","Place":"","Name":"Coswig Auerstraße","Longitude":4610339,"Latitude":5668411,"Position":"Previous","Platform":{"Name":"1","Type":"Platform"},"Time":"2022-02-21 03:51:00","RealTime":"2022-02-21 03:51:00","State":"InTime"},{"Id":"33004156","DhId":"de:14627:4156","Place":"","Name":"Coswig Salzstraße","Longitude":4610574,"Latitude":5668011,"Position":"Previous","Platform":{"Name":"1","Type":"Platform"},"Time":"2022-02-21 03:52:00","RealTime":"2022-02-21 03:53:00","State":"Delayed"},{"Id":"33004185","DhId":"de:14627:4185","Place":"","Name":"Coswig Rathaus","Longitude":4610574,"Latitude":5667052,"Position":"Previous","Platform":{"Name":"1","Type":"Platform"},"Time":"2022-02-21 03:54:00","RealTime":"2022-02-21 03:55:00","State":"Delayed"},{"Id":"33004160","DhId":"de:14627:4160","Place":"","Name":"Coswig Zentrum/ Börse","Longitude":4610779,"Latitude":5666989,"Position":"Previous","Platform":{"Name":"3","Type":"Platform"},"Time":"2022-02-21 03:55:00","RealTime":"2022-02-21 03:56:00","State":"Delayed"},{"Id":"33004168","DhId":"de:14627:4168","Place":"","Name":"Coswig Radebeuler Straße","Longitude":4611320,"Latitude":5666833,"Position":"Previous","Platform":{"Name":"2","Type":"Platform"},"Time":"2022-02-21 03:57:00","RealTime":"2022-02-21 03:58:00","State":"Delayed"},{"Id":"33004230","DhId":"de:14627:4230","Place":"","Name":"Radebeul Eisenbahnbrücke","Longitude":4611765,"Latitude":5666319,"Position":"Previous","Platform":{"Name":"1","Type":"Platform"},"Time":"2022-02-21 03:58:00","RealTime":"2022-02-21 03:59:00","State":"Delayed"},{"Id":"33004229","DhId":"de:14627:4229","Place":"","Name":"Radebeul Gerhart-Hauptmann-Straße","Longitude":4612352,"Latitude":5666201,"Position":"Previous","Platform":{"Name":"1","Type":"Platform"},"Time":"2022-02-21 04:00:00","RealTime":"2022-02-21 04:01:00","State":"Delayed"},{"Id":"33004228","DhId":"de:14627:4228","Place":"","Name":"Radebeul Johannisbergstraße","Longitude":4612966,"Latitude":5665613,"Position":"Previous","Platform":{"Name":"1","Type":"Platform"},"Time":"2022-02-21 04:02:00","RealTime":"2022-02-21 04:03:00","State":"Delayed"},{"Id":"33004227","DhId":"de:14627:4227","Place":"","Name":"Radebeul Schloss Wackerbarth","Longitude":4613451,"Latitude":5665446,"Position":"Previous","Platform":{"Name":"1","Type":"Platform"},"Time":"2022-02-21 04:03:00","RealTime":"2022-02-21 04:04:00","State":"Delayed"},{"Id":"33004226","DhId":"de:14627:4226","Place":"","Name":"Radebeul West (Flemmingstraße)","Longitude":4613866,"Latitude":5665201,"Position":"Previous","Platform":{"Name":"1","Type":"Platform"},"Time":"2022-02-21 04:04:00","RealTime":"2022-02-21 04:05:00","State":"Delayed"},{"Id":"33004225","DhId":"de:14627:4225","Place":"","Name":"Radebeul Moritzburger Straße","Longitude":4614199,"Latitude":5664973,"Position":"Previous","Platform":{"Name":"3","Type":"Platform"},"Time":"2022-02-21 04:05:00","RealTime":"2022-02-21 04:06:00","State":"Delayed"},{"Id":"33004233","DhId":"de:14627:4233","Place":"","Name":"Radebeul Gradsteg","Longitude":4614637,"Latitude":5664864,"Position":"Previous","Platform":{"Name":"1","Type":"Platform"},"Time":"2022-02-21 04:06:00","RealTime":"2022-02-21 04:07:00","State":"Delayed"},{"Id":"33004224","DhId":"de:14627:4224","Place":"","Name":"Radebeul Borstraße","Longitude":4614919,"Latitude":5664800,"Position":"Previous","Platform":{"Name":"1","Type":"Platform"},"Time":"2022-02-21 04:07:00","RealTime":"2022-02-21 04:09:00","State":"Delayed"},{"Id":"33004223","DhId":"de:14627:4223","Place":"","Name":"Radebeul Dr.-Külz-Straße","Longitude":4615427,"Latitude":5664753,"Position":"Previous","Platform":{"Name":"1","Type":"Platform"},"Time":"2022-02-21 04:08:00","RealTime":"2022-02-21 04:10:00","State":"Delayed"},{"Id":"33004222","DhId":"de:14627:4222","Place":"","Name":"Radebeul Zillerstraße","Longitude":4615912,"Latitude":5664688,"Position":"Previous","Platform":{"Name":"1","Type":"Platform"},"Time":"2022-02-21 04:09:00","RealTime":"2022-02-21 04:10:00","State":"Delayed"},{"Id":"33004221","DhId":"de:14627:4221","Place":"","Name":"Radebeul Landesbühnen Sachsen","Longitude":4616378,"Latitude":5664753,"Position":"Previous","Platform":{"Name":"1","Type":"Platform"},"Time":"2022-02-21 04:10:00","RealTime":"2022-02-21 04:11:00","State":"Delayed"},{"Id":"33004219","DhId":"de:14627:4219","Place":"","Name":"Radebeul Wasastraße","Longitude":4616955,"Latitude":5664554,"Position":"Previous","Platform":{"Name":"1","Type":"Platform"},"Time":"2022-02-21 04:11:00","RealTime":"2022-02-21 04:13:00","State":"Delayed"},{"Id":"33004218","DhId":"de:14627:4218","Place":"","Name":"Radebeul Schildenstraße","Longitude":4617265,"Latitude":5664527,"Position":"Previous","Platform":{"Name":"1","Type":"Platform"},"Time":"2022-02-21 04:12:00","RealTime":"2022-02-21 04:14:00","State":"Delayed"},{"Id":"33004217","DhId":"de:14627:4217","Place":"","Name":"Radebeul Hauptstraße","Longitude":4617821,"Latitude":5664377,"Position":"Previous","Platform":{"Name":"1","Type":"Platform"},"Time":"2022-02-21 04:14:00","RealTime":"2022-02-21 04:16:00","State":"Delayed"},{"Id":"33004216","DhId":"de:14627:4216","Place":"","Name":"Radebeul Zinzendorfstraße","Longitude":4618103,"Latitude":5664240,"Position":"Previous","Platform":{"Name":"1","Type":"Platform"},"Time":"2022-02-21 04:15:00","RealTime":"2022-02-21 04:17:00","State":"Delayed"},{"Id":"33004214","DhId":"de:14627:4214","Place":"","Name":"Radebeul Forststraße","Longitude":4618785,"Latitude":5663724,"Position":"Previous","Platform":{"Name":"1","Type":"Platform"},"Time":"2022-02-21 04:17:00","RealTime":"2022-02-21 04:19:00","State":"Delayed"},{"Id":"33000213","DhId":"de:14612:213","Place":"","Name":"Dresden Kleestraße","Longitude":4619165,"Latitude":5663315,"Position":"Previous","Platform":{"Name":"1","Type":"Platform"},"Time":"2022-02-21 04:18:00","RealTime":"2022-02-21 04:20:00","State":"Delayed"},{"Id":"33000212","DhId":"de:14612:212","Place":"","Name":"Dresden S-Bahnhof Trachau West","Longitude":4619346,"Latitude":5663117,"Position":"Previous","Platform":{"Name":"1","Type":"Platform"},"Time":"2022-02-21 04:19:00","RealTime":"2022-02-21 04:21:00","State":"Delayed"},{"Id":"33000211","DhId":"de:14612:211","Place":"","Name":"Dresden Peschelstraße","Longitude":4619457,"Latitude":5662847,"Position":"Previous","Platform":{"Name":"1","Type":"Platform"},"Time":"2022-02-21 04:20:00","RealTime":"2022-02-21 04:22:00","State":"Delayed"},{"Id":"33000210","DhId":"de:14612:210","Place":"","Name":"Dresden Rankestraße","Longitude":4619566,"Latitude":5662533,"Position":"Previous","Platform":{"Name":"1","Type":"Platform"},"Time":"2022-02-21 04:21:00","RealTime":"2022-02-21 04:23:00","State":"Delayed"},{"Id":"33000209","DhId":"de:14612:209","Place":"","Name":"Dresden Alttrachau","Longitude":4619807,"Latitude":5662416,"Position":"Previous","Platform":{"Name":"1","Type":"Platform"},"Time":"2022-02-21 04:22:00","RealTime":"2022-02-21 04:24:00","State":"Delayed"},{"Id":"33000205","DhId":"de:14612:205","Place":"","Name":"Dresden Mickten","Longitude":4620225,"Latitude":5661942,"Position":"Previous","Platform":{"Name":"1","Type":"Platform"},"Time":"2022-02-21 04:24:00","RealTime":"2022-02-21 04:25:00","State":"Delayed"},{"Id":"33000200","DhId":"de:14612:200","Place":"","Name":"Dresden Altpieschen","Longitude":4620480,"Latitude":5661673,"Position":"Previous","Platform":{"Name":"3","Type":"Platform"},"Time":"2022-02-21 04:25:00","RealTime":"2022-02-21 04:26:00","State":"Delayed"},{"Id":"33000245","DhId":"de:14612:245","Place":"","Name":"Dresden Rathaus Pieschen","Longitude":4620776,"Latitude":5661663,"Position":"Previous","Platform":{"Name":"1","Type":"Platform"},"Time":"2022-02-21 04:26:00","RealTime":"2022-02-21 04:27:00","State":"Delayed"},{"Id":"33000244","DhId":"de:14612:244","Place":"","Name":"Dresden Bürgerstraße","Longitude":4621052,"Latitude":5661611,"Position":"Previous","Platform":{"Name":"1","Type":"Platform"},"Time":"2022-02-21 04:27:00","RealTime":"2022-02-21 04:28:00","State":"Delayed"},{"Id":"33000243","DhId":"de:14612:243","Place":"","Name":"Dresden Liststraße","Longitude":4621430,"Latitude":5661647,"Position":"Previous","Platform":{"Name":"5","Type":"Platform"},"Time":"2022-02-21 04:28:00","RealTime":"2022-02-21 04:29:00","State":"Delayed"},{"Id":"33000248","DhId":"de:14612:248","Place":"","Name":"Dresden Zeithainer Straße","Longitude":4621337,"Latitude":5662241,"Position":"Previous","Platform":{"Name":"2","Type":"Platform"},"Time":"2022-02-21 04:29:00","RealTime":"2022-02-21 04:30:00","State":"Delayed"},{"Id":"33000249","DhId":"de:14612:249","Place":"","Name":"Dresden Trachenberger Platz","Longitude":4621206,"Latitude":5662436,"Position":"Current","Platform":{"Name":"3","Type":"Platform"},"Time":"2022-02-21 04:30:00","RealTime":"2022-02-21 04:31:00","State":"Delayed"},{"Id":"33000250","DhId":"de:14612:250","Place":"","Name":"Dresden Betriebshof Trachenberge","Longitude":4621270,"Latitude":5662746,"Position":"Next","Platform":{"Name":"2","Type":"Platform"},"Time":"2022-02-21 04:31:00","RealTime":"2022-02-21 04:32:00","State":"Delayed"}]
